gerencianet/__init__.py
gerencianet/constants.py
gerencianet/endpoints.py
gerencianet/exceptions.py
gerencianet/gerencianet.py
gerencianet/version.py
test/__init__.py
test/test_gerencianet.py
gerencianet-3.0.0.dist-info/LICENSE
gerencianet-3.0.0.dist-info/METADATA
gerencianet-3.0.0.dist-info/WHEEL
gerencianet-3.0.0.dist-info/top_level.txt
gerencianet-3.0.0.dist-info/RECORD
