Metadata-Version: 2.1
Name: gerencianet
Version: 3.0.0
Summary: Module for integration with Gerencianet API
Home-page: https://github.com/gerencianet/gn-api-sdk-python
Author: Danniel Hugo, Cecilia Deveza, Francisco Thiene, Thomaz Feitoza, Talita Campos, Matheus Rodrigues, Palloma Brito
Author-email: suportetecnico@gerencianet.com.br
License: MIT
Keywords: payment Gerencianet
Classifier: Development Status :: 5 - Production/Stable
Classifier: Intended Audience :: Developers
Classifier: Topic :: Software Development
Classifier: License :: OSI Approved :: MIT License
Classifier: Programming Language :: Python :: 2.7
Classifier: Programming Language :: Python :: 3.3
Classifier: Programming Language :: Python :: 3.4
Classifier: Programming Language :: Python :: 3.5
Classifier: Programming Language :: Python :: 3.9
Provides-Extra: test
License-File: LICENSE
